github_stats/__init__.py
github_stats/app.py
github_stats/rich_utils.py
github_stats-0.0.3.dist-info/LICENSE
github_stats-0.0.3.dist-info/METADATA
github_stats-0.0.3.dist-info/WHEEL
github_stats-0.0.3.dist-info/entry_points.txt
github_stats-0.0.3.dist-info/top_level.txt
github_stats-0.0.3.dist-info/RECORD
