Metadata-Version: 2.1
Name: github-stats
Version: 0.0.3
Summary: Command line tool to get number of PRs reviewed by a user
Home-page: https://github.com/saiyalamarty/github-stats
Author: Sai Yalamarty
Author-email: sai1494@gmail.com
License: MIT
Classifier: Development Status :: 4 - Beta
Classifier: Intended Audience :: Developers
Classifier: License :: OSI Approved :: MIT License
Classifier: Operating System :: OS Independent
Classifier: Topic :: Software Development :: Version Control :: Git
Classifier: Programming Language :: Python :: 3.8
Classifier: Programming Language :: Python :: 3.9
Classifier: Programming Language :: Python :: 3.10
Requires-Python: >=3.8
License-File: LICENSE
Requires-Dist: click (>=8.1.3)
Requires-Dist: pandas (>=1.4.3)
Requires-Dist: PyGithub (>=1.55)
Requires-Dist: python-dotenv (>=0.20.0)
Requires-Dist: rich (>=12.5.1)
